setup.py
distributions_TWEETY/Binomialdistribution.py
distributions_TWEETY/Gaussiandistribution.py
distributions_TWEETY/Generaldistribution.py
distributions_TWEETY/__init__.py
distributions_TWEETY.egg-info/PKG-INFO
distributions_TWEETY.egg-info/SOURCES.txt
distributions_TWEETY.egg-info/dependency_links.txt
distributions_TWEETY.egg-info/not-zip-safe
distributions_TWEETY.egg-info/top_level.txt